Workbook

Sheet Read Me
A1: JONIK NDOVU FARM — VERSION 3.0 FINANCIAL WORKING MODEL
A3: Status | B3: Illustrative placeholder model — not an investment-grade forecast
A4: Fixed project brief | B4: US$2.4m total capital requirement including proposed additional land acquisition
A5: Accommodation | B5: 12–15 units; base case uses 12 units, 15-unit sensitivity separate
A6: Important | B6: Replace every yellow input with verified land, QS, market, tax and operating data before investor use.
A8: Currency | B8: USD
A9: Model convention | B9: Unlevered operating illustration; no financing, tax, depreciation or exit proceeds included.
A10: Do not rely on output | B10: Occupancy, ADR, revenue, EBITDA and payback are placeholders only.

Sheet Inputs
A1: Input | B1: Value | C1: Units / note | D1: Status
A2: Total capital requirement | B2: 2400000 | C2: USD; includes proposed additional land acquisition | D2: Project brief
A3: Base accommodation units | B3: 12 | C3: units; 15-unit case can be modelled by changing input | D3: Developer-surveyed range 12–15
A4: Available nights per unit | B4: 365 | C4: nights per year | D4: Assumption
A5: Stabilized occupancy | B5: 0.55 | C5: % of available unit nights | D5: PLACEHOLDER — validate
A6: Year 1 occupancy | B6: 0.3 | C6: % | D6: PLACEHOLDER — ramp-up
A7: Year 2 occupancy | B7: 0.4 | C7: % | D7: PLACEHOLDER — ramp-up
A8: Year 3 occupancy | B8: 0.48 | C8: % | D8: PLACEHOLDER — ramp-up
A9: Average daily rate (ADR) | B9: 280 | C9: USD per occupied unit night | D9: PLACEHOLDER — market study needed
A10: Other revenue as % room revenue | B10: 0.45 | C10: % food, beverage and experiences | D10: PLACEHOLDER — validate
A11: Direct operating costs as % total revenue | B11: 0.38 | C11: % | D11: PLACEHOLDER — validate
A12: Payroll & admin as % total revenue | B12: 0.25 | C12: % | D12: PLACEHOLDER — validate
A13: Sales & distribution as % total revenue | B13: 0.08 | C13: % | D13: PLACEHOLDER — validate
... A22: Contingency | B22: 0 | C22: USD; set based on cost plan maturity | D22: NOT YET VERIFIED

Sheet 10-Year Model
A1: Metric | B1: Year 1 | C1: Year 2 | D1: Year 3 | E1: Year 4 | F1: Year 5 | G1: Year 6 | H1: Year 7 | I1: Year 8 | J1: Year 9 | K1: Year 10
A2: Units | B2: =Inputs!B4 | C2: =Inputs!B4 | D2: =Inputs!B4 | E2: =Inputs!B4 | F2: =Inputs!B4 | G2: =Inputs!B4 | H2: =Inputs!B4 | I2: =Inputs!B4 | J2: =Inputs!B4 | K2: =Inputs!B4
A3: Occupancy | B3: =Inputs!B6 | C3: =Inputs!B7 | D3: =Inputs!B8 | E3: =Inputs!B5 | F3: =Inputs!B5 | G3: =Inputs!B5 | H3: =Inputs!B5 | I3: =Inputs!B5 | J3: =Inputs!B5 | K3: =Inputs!B5
A4: Available unit nights | B4: =B2*Inputs!B4 | C4: =C2*Inputs!B4 | D4: =D2*Inputs!B4 | E4: =E2*Inputs!B4 | F4: =F2*Inputs!B4 | G4: =G2*Inputs!B4 | H4: =H2*Inputs!B4 | I4: =I2*Inputs!B4 | J4: =J2*Inputs!B4 | K4: =K2*Inputs!B4
A5: Occupied unit nights | B5: =B4*B3 | C5: =C4*C3 | D5: =D4*D3 | E5: =E4*E3 | F5: =F4*F3 | G5: =G4*G3 | H5: =H4*H3 | I5: =I4*I3 | ... K5: =K4*K3
A6: ADR | B6: =Inputs!B10 | C6: =Inputs!B10 | D6: =Inputs!B10 | E6: =Inputs!B10 | F6: =Inputs!B10 | G6: =Inputs!B10 | H6: =Inputs!B10 | I6: =Inputs!B10 | J6: =Inputs!B10 | K6: =Inputs!B10
A7: Room revenue | B7: =B5*B6 | C7: =C5*C6 | D7: =D5*D6 | E7: =E5*E6 | F7: =F5*F6 | G7: =G5*G6 | H7: =H5*H6 | I7: =I5*I6 | ... K7: =K5*K6
A8: Other revenue | B8: =B7*Inputs!B11 | C8: =C7*Inputs!B11 | D8: =D7*Inputs!B11 | E8: =E7*Inputs!B11 | F8: =F7*Inputs!B11 | G8: =G7*Inputs!B11 | H8: =H7*Inputs!B11 | I8: =I7*Inputs!B11 | J8: =J7*Inputs!B11 | K8: =K7*Inputs!B11
A9: Total revenue | B9: =B7+B8 | C9: =C7+C8 | D9: =D7+D8 | E9: =E7+E8 | F9: =F7+F8 | G9: =G7+G8 | H9: =H7+H8 | I9: =I7+I8 | ... K9: =K7+K8
A10: Direct operating costs | B10: =B9*Inputs!B12 | C10: =C9*Inputs!B12 | D10: =D9*Inputs!B12 | E10: =E9*Inputs!B12 | F10: =F9*Inputs!B12 | G10: =G9*Inputs!B12 | H10: =H9*Inputs!B12 | I10: =I9*Inputs!B12 | J10: =J9*Inputs!B12 | K10: =K9*Inputs!B12
A11: Payroll & admin | B11: =B9*Inputs!B13 | C11: =C9*Inputs!B13 | D11: =D9*Inputs!B13 | E11: =E9*Inputs!B13 | F11: =F9*Inputs!B13 | G11: =G9*Inputs!B13 | H11: =H9*Inputs!B13 | I11: =I9*Inputs!B13 | J11: =J9*Inputs!B13 | K11: =K9*Inputs!B13
A12: Sales & distribution | B12: =B9*Inputs!B14 | C12: =C9*Inputs!B14 | D12: =D9*Inputs!B14 | E12: =E9*Inputs!B14 | F12: =F9*Inputs!B14 | G12: =G9*Inputs!B14 | H12: =H9*Inputs!B14 | I12: =I9*Inputs!B14 | J12: =J9*Inputs!B14 | K12: =K9*Inputs!B14
A13: Repairs/utilities/other opex | B13: =B9*Inputs!B15 | C13: =C9*Inputs!B15 | D13: =D9*Inputs!B15 | E13: =E9*Inputs!B15 | F13: =F9*Inputs!B15 | G13: =G9*Inputs!B15 | H13: =H9*Inputs!B15 | I13: =I9*Inputs!B15 | J13: =J9*Inputs!B15 | K13: =K9*Inputs!B15
A14: Illustrative EBITDA | B14: =B9-B10-B11-B12-B13 | C14: =C9-C10-C11-C12-C13 | D14: =D9-D10-D11-D12-D13 | E14: =E9-E10-E11-E12-E13 | F14: =F9-F10-F11-F12-F13 | G14: =G9-G10-G11-G12-G13 | H14: =H9-H10-H11-H12-H13 | I14: =I9-I10-I11-I12-I13 | ... K14: =K9-K10-K11-K12-K13
A15: Maintenance capex | B15: =B9*Inputs!B16 | C15: =C9*Inputs!B16 | D15: =D9*Inputs!B16 | E15: =E9*Inputs!B16 | F15: =F9*Inputs!B16 | G15: =G9*Inputs!B16 | H15: =H9*Inputs!B16 | I15: =I9*Inputs!B16 | J15: =J9*Inputs!B16 | K15: =K9*Inputs!B16
A16: Illustrative cash before financing/tax | B16: =B14-B15 | C16: =C14-C15 | D16: =D14-D15 | E16: =E14-E15 | F16: =F14-F15 | G16: =G14-G15 | H16: =H14-H15 | I16: =I14-I15 | ... K16: =K14-K15

Sheet Sources & Uses
A1: USES OF FUNDS | B1: USD | C1: Evidence / status
A2: Land acquisition incl transaction costs | B2: 0 | C2: Enter verified written offer; included in US$2.4m total
A3: Construction and infrastructure | B3: 0 | C3: QS cost plan required
A4: FF&E / OS&E | B4: 0 | C4: Supplier-backed estimate required
A5: Professional fees and approvals | B5: 0 | C5: Advisor estimates required
A6: Pre-opening and working capital | B6: 0 | C6: Operating plan required
A7: Contingency | B7: 0 | C7: QS recommendation required
A8: TOTAL USES | B8: =SUM(B2:B7) | C8: Must reconcile to US$2,400,000
A10: SOURCES OF CAPITAL | B10: USD | C10: Status
A11: Equity | B11: 2400000 | C11: Placeholder only; structure not agreed
A12: Debt | B12: 0 | C12: Do not assume debt without lender terms and debt-service capacity
A13: Other sources | B13: 0 | C13: Only if documented
A14: TOTAL SOURCES | B14: =SUM(B11:B13) | C14: Must equal total uses
A15: Funding surplus / (gap) | B15: =B14-B8 | C15: Must be zero at final funding plan

Sheet Scenario Compare
A1: Scenario | B1: Units | C1: Total capex USD | D1: Stabilized occupancy | E1: ADR USD | F1: Annual room revenue USD | G1: Total revenue incl other USD | H1: EBITDA USD | I1: Status
A2: Phased / 12-unit base | B2: 12 | C2: 2400000 | D2: 0.55 | E2: 280 | F2: =B2*365*D2*E2 | G2: =F2*(1+Inputs!B11) | H2: =G2*(1-Inputs!B12-Inputs!B13-Inputs!B14-Inputs!B15) | I2: Illustrative; phased capex and timing not modelled
A3: Full / 15-unit sensitivity | B3: 15 | C3: 2400000 | D3: 0.55 | E3: 280 | F3: =B3*365*D3*E3 | G3: =F3*(1+Inputs!B11) | H3: =G3*(1-Inputs!B12-Inputs!B13-Inputs!B14-Inputs!B15) | I3: Illustrative; same capex assumption is not validated
